{"otherData": {},"traceEvents":[{"cat":"function","dur":18,"name":"glm::dmat4x4 getRotationMatrix(double, double, double)","ph":"X","pid":0,"tid":852934278,"ts":1689069367416560},{"cat":"function","dur":2,"name":"glm::dmat4x4 getRotationMatrix(double, double, double)","ph":"X","pid":0,"tid":852934278,"ts":1689069367416613},{"cat":"function","dur":2689086,"name":"importBeamline","ph":"X","pid":0,"tid":852934278,"ts":1689069367415223},{"cat":"function","dur":318232,"name":"getInputRays","ph":"X","pid":0,"tid":852934278,"ts":1689069370104403},{"cat":"function","dur":10456,"name":"traceRaw","ph":"X","pid":0,"tid":852934278,"ts":1689069370425017},{"cat":"function","dur":10495,"name":"Tracing","ph":"X","pid":0,"tid":852934278,"ts":1689069370425017},{"cat":"function","dur":8315,"name":"Snapshoting","ph":"X","pid":0,"tid":852934278,"ts":1689069370435516},{"cat":"function","dur":339745,"name":"trace","ph":"X","pid":0,"tid":852934278,"ts":1689069370104401},{"cat":"function","dur":4547663,"name":"exportRays","ph":"X","pid":0,"tid":852934278,"ts":1689069370444155},{"cat":"function","dur":7578185,"name":"void TerminalApp::run()","ph":"X","pid":0,"tid":852934278,"ts":1689069367414699}]}